quorapy/__init__.py
quorapy/browser.py
quorapy/quora.py
quorapy/scraper.py
quorapy-0.1.0.dist-info/DESCRIPTION.rst
quorapy-0.1.0.dist-info/METADATA
quorapy-0.1.0.dist-info/RECORD
quorapy-0.1.0.dist-info/WHEEL
quorapy-0.1.0.dist-info/metadata.json
quorapy-0.1.0.dist-info/top_level.txt
