Metadata-Version: 2.0
Name: quorapy
Version: 0.1.0
Summary: Fetches and parses data from Quora.
Home-page: https://github.com/djunehor/quorapy
Author: Zacchaeus Bolaji
Author-email: djunehor@gmail.com
License: UNKNOWN
Platform: UNKNOWN
Requires-Dist: beautifulsoup4
Requires-Dist: dateparser
Requires-Dist: feedparser
Requires-Dist: lxml
Requires-Dist: selenium
